tartarus.py
tartarus-0.2.3.dist-info/METADATA
tartarus-0.2.3.dist-info/WHEEL
tartarus-0.2.3.dist-info/entry_points.txt
tartarus-0.2.3.dist-info/top_level.txt
tartarus-0.2.3.dist-info/RECORD
