Metadata-Version: 2.1
Name: tartarus
Version: 0.2.3
Summary: UNKNOWN
Home-page: UNKNOWN
Author: UNKNOWN
Author-email: UNKNOWN
License: UNKNOWN
Platform: UNKNOWN
Requires-Dist: Click
Requires-Dist: colorama
Requires-Dist: hexrec
